sakura/__init__.py
sakura/agent.py
sakura/exceptions.py
sakura/media.py
sakura/py.typed
sakura/run.py
sakuragent-0.3.3.dist-info/licenses/LICENSE
sakuragent-0.3.3.dist-info/METADATA
sakuragent-0.3.3.dist-info/WHEEL
sakuragent-0.3.3.dist-info/top_level.txt
sakuragent-0.3.3.dist-info/RECORD
