Metadata-Version: 2.4
Name: sakuragent
Version: 0.3.3
Summary: Sakura Agent Framework - A streamlined LLM agent framework
Author-email: Vist233 <zhangyvjing@outlook.com>
License: MIT
Project-URL: Homepage, https://github.com/Vist233/sakura
Project-URL: Bug Tracker, https://github.com/Vist233/sakura/issues
Project-URL: Source Code, https://github.com/Vist233/sakura
Keywords: llm,agent,framework,performance,sakura,sakuragent
Classifier: Programming Language :: Python :: 3
Classifier: Programming Language :: Python :: 3.10
Classifier: Programming Language :: Python :: 3.11
Classifier: Programming Language :: Python :: 3.12
Classifier: License :: OSI Approved :: MIT License
Classifier: Operating System :: OS Independent
Requires-Python: >=3.10
License-File: LICENSE
Requires-Dist: pydantic>=2.0
Requires-Dist: openai>=1.0
Requires-Dist: rich
Requires-Dist: docstring-parser
Requires-Dist: packaging
Requires-Dist: pyyaml
Requires-Dist: python-dotenv
Provides-Extra: qwen
Requires-Dist: dashscope; extra == "qwen"
Provides-Extra: claude
Requires-Dist: anthropic; extra == "claude"
Provides-Extra: search
Requires-Dist: ddgs; extra == "search"
Provides-Extra: dev
Requires-Dist: pytest; extra == "dev"
Requires-Dist: pytest-asyncio; extra == "dev"
Provides-Extra: all
Requires-Dist: sakura[claude,dev,qwen,search]; extra == "all"
Dynamic: license-file
